[
  {
    "id": 1,
    "name": "Joker",
    "front": "Joker",
    "revert": "Joker Ters",
    "enFront": "The fool",
    "enRevert": "The fool - revert",
    "image": "falfalFE/public/images/cards/joker.png"
  },
  {
    "id": 2,
    "name": "Büyücü",
    "front": "Büyücü",
    "revert": "Büyücü Ters",
    "enFront": "The magician",
    "enRevert": "The magician - revert",
    "image": "falfalFE/public/images/cards/buyucu.png"
  },
  {
    "id": 2,
    "name": "Azice",
    "front": "Azice",
    "revert": "Azice Ters",
    "enFront": "The High Priestess",
    "enRevert": "The High Priestess - revert",
    "image": "falfalFE/public/images/cards/azize.png"
  },
  {
    "id": 3,
    "name": "İmparatoriçe",
    "front": "İmparatoriçe",
    "revert": "İmparatoriçe Ters",
    "enFront": "The Empress",
    "enRevert": "The Empress - revert",
    "image": "falfalFE/public/images/cards/imparatorice.png"
  },
  {
    "id": 4,
    "name": "İmparator",
    "front": "İmparator",
    "revert": "İmparator Ters",
    "enFront": "The Emperor",
    "enRevert": "The Emperor - revert",
    "image": "falfalFE/public/images/cards/imparator.png"
  },
  {
    "id": 5,
    "name": "Aziz",
    "front": "Aziz",
    "revert": "Aziz Ters",
    "enFront": "The Hierophant",
    "enRevert": "The Hierophant - revert",
    "image": "falfalFE/public/images/cards/aziz.png"
  },
  {
    "id": 6,
    "name": "AşıK",
    "front": "AşıK",
    "revert": "AşıK Ters",
    "enFront": "The Lovers",
    "enRevert": "The Lovers - revert",
    "image": "falfalFE/public/images/cards/asik.png"
  },
  {
    "id": 7,
    "name": "Araba",
    "front": "Araba",
    "revert": "Araba Ters",
    "enFront": "The Chariot",
    "enRevert": "The Chariot - revert",
    "image": "falfalFE/public/images/cards/araba.png"
  },
  {
    "id": 8,
    "name": "Güç",
    "front": "Güç",
    "revert": "Güç Ters",
    "enFront": "Strength",
    "enRevert": "Strength - revert",
    "image": "falfalFE/public/images/cards/guc.png"
  },
  {
    "id": 9,
    "name": "Ermiş",
    "front": "Ermiş",
    "revert": "Ermiş Ters",
    "enFront": "The Hermit",
    "enRevert": "The Hermit - revert",
    "image": "falfalFE/public/images/cards/ermis.png"
  },
  {
    "id": 10,
    "name": "Kader Çarkı",
    "front": "Kader Çarkı",
    "revert": "Kader Çarkı Ters",
    "enFront": "Wheel of Fortune",
    "enRevert": "Wheel of Fortune - revert",
    "image": "falfalFE/public/images/cards/kader-carki.png"
  },
  {
    "id": 11,
    "name": "Adalet",
    "front": "Adalet",
    "revert": "Adalet Ters",
    "enFront": "Justice",
    "enRevert": "Justice - revert",
    "image": "falfalFE/public/images/cards/adalet.png"
  },
  {
    "id": 12,
    "name": "Asılan Adam",
    "front": "Asılan Adam",
    "revert": "Asılan Adam Ters",
    "enFront": "The Hanged Man",
    "enRevert": "The Hanged Man Revert",
    "image": "falfalFE/public/images/cards/asilan-adam.png"
  },
  {
    "id": 13,
    "name": "Ölüm",
    "front": "Ölüm",
    "revert": "Ölüm Ters",
    "enFront": "Death",
    "enRevert": "Death - revert",
    "image": "falfalFE/public/images/cards/olum.png"
  },
  {
    "id": 14,
    "name": "Denge",
    "front": "Denge",
    "revert": "Denge Ters",
    "enFront": "Temperance",
    "enRevert": "Temperance - revert",
    "image": "falfalFE/public/images/cards/denge.png"
  },
  {
    "id": 15,
    "name": "Şeytan",
    "front": "Şeytan",
    "revert": "Şeytan Ters",
    "enFront": "The Devil",
    "enRevert": "The Devil - revert",
    "image": "falfalFE/public/images/cards/seytan.png"
  },
  {
    "id": 16,
    "name": "Kule",
    "front": "Kule",
    "revert": "Kule Ters",
    "enFront": "The Tower",
    "enRevert": "The Tower - revert",
    "image": "falfalFE/public/images/cards/kule.png"
  },
  {
    "id": 17,
    "name": "Yıldız",
    "front": "Yıldız",
    "revert": "Yıldız Ters",
    "enFront": "The Star",
    "enRevert": "The Star - revert",
    "image": "falfalFE/public/images/cards/yildiz.png"
  },
  {
    "id": 18,
    "name": "Ay",
    "front": "Ay",
    "revert": "Ay Ters",
    "enFront": "The Moon",
    "enRevert": "The Moon - revert",
    "image": "falfalFE/public/images/cards/ay.png"
  },
  {
    "id": 19,
    "name": "Güneş",
    "front": "Güneş",
    "revert": "Güneş Ters",
    "enFront": "The Sun",
    "enRevert": "The Sun - revert",
    "image": "falfalFE/public/images/cards/gunes.png"
  },
  {
    "id": 20,
    "name": "Yargı",
    "front": "Yargı",
    "revert": "Yargı Ters",
    "enFront": "Judgement",
    "enRevert": "Judgement - revert",
    "image": "falfalFE/public/images/cards/yargi.png"
  },
  {
    "id": 21,
    "name": "Dünya",
    "front": "Dünya",
    "revert": "Dünya Ters",
    "enFront": "The World",
    "enRevert": "The World - revert",
    "image": "falfalFE/public/images/cards/dunya.png"
  },
  {
    "id": 22,
    "name": "Kılıç Ası",
    "front": "Kılıç Ası",
    "revert": "Kılıç Ası Ters",
    "enFront": "Ace of Swords",
    "enRevert": "Ace of Swords - revert",
    "image": "falfalFE/public/images/cards/kilic-asi.png"
  },
  {
    "id": 23,
    "name": "Kılıç İkilisi",
    "front": "Kılıç İkilisi",
    "revert": "Kılıç İkilisi Ters",
    "enFront": "Two of Swords",
    "enRevert": "Two of Swords - revert",
    "image": "falfalFE/public/images/cards/kilic-ikilisi.png"
  },
  {
    "id": 24,
    "name": "Kılıç Üçlüsü",
    "front": "Kılıç Üçlüsü",
    "revert": "Kılıç Üçlüsü Ters",
    "enFront": "Three of Swords",
    "enRevert": "Three of Swords - revert",
    "image": "falfalFE/public/images/cards/kilic-uclusu.png"
  },
  {
    "id": 25,
    "name": "Kılıç Dörtlüsü",
    "front": "Kılıç Dörtlüsü",
    "revert": "Kılıç Dörtlüsü Ters",
    "enFront": "Four of Swords",
    "enRevert": "Four of Swords - revert",
    "image": "falfalFE/public/images/cards/kilic-dortlusu.png"
  },
  {
    "id": 26,
    "name": "Kılıç Beşlisi",
    "front": "Kılıç Beşlisi",
    "revert": "Kılıç Beşlisi Ters",
    "enFront": "Five of Swords",
    "enRevert": "Five of Swords - revert",
    "image": "falfalFE/public/images/cards/kilic-beslisi.png"
  },
  {
    "id": 27,
    "name": "Kılıç Altılısı",
    "front": "Kılıç Altılısı",
    "revert": "Kılıç Altılısı Ters",
    "enFront": "Six of Swords",
    "enRevert": "Six of Swords - revert",
    "image": "falfalFE/public/images/cards/kilic-altilisi.png"
  },
  {
    "id": 28,
    "name": "Kılıç Yedilisi",
    "front": "Kılıç Yedilisi",
    "revert": "Kılıç Yedilisi Ters",
    "enFront": "Seven of Swords",
    "enRevert": "Seven of Swords - revert",
    "image": "falfalFE/public/images/cards/kilic-yedilisi.png"
  },
  {
    "id": 29,
    "name": "Kılıç Sekizlisi",
    "front": "Kılıç Sekizlisi",
    "revert": "Kılıç Sekizlisi Ters",
    "enFront": "Eight of Swords",
    "enRevert": "Eight of Swords - revert",
    "image": "falfalFE/public/images/cards/kilic-sekizlisi.png"
  },
  {
    "id": 30,
    "name": "Kılıç Dokuzlusu",
    "front": "Kılıç Dokuzlusu",
    "revert": "Kılıç Dokuzlusu Ters",
    "enFront": "Nine of Swords",
    "enRevert": "Nine of Swords - revert",
    "image": "falfalFE/public/images/cards/kilic-dokuzlusu.png"
  },
  {
    "id": 31,
    "name": "Kılıç Onlusu",
    "front": "Kılıç Onlusu",
    "revert": "Kılıç Onlusu Ters",
    "enFront": "Ten of Swords",
    "enRevert": "Ten of Swords - revert",
    "image": "falfalFE/public/images/cards/kilic-onlusu.png"
  },
  {
    "id": 32,
    "name": "Kılıç Prensi",
    "front": "Kılıç Prensi",
    "revert": "Kılıç Prensi Ters",
    "enFront": "Page of Swords",
    "enRevert": "Page of Swords - revert",
    "image": "falfalFE/public/images/cards/kilic-prensi.png"
  },
  {
    "id": 33,
    "name": "Kılıç Şövalyesi",
    "front": "Kılıç Şövalyesi",
    "revert": "Kılıç Şövalyesi Ters",
    "enFront": "Knight of Swords",
    "enRevert": "Knight of Swords - revert",
    "image": "falfalFE/public/images/cards/kilic-sovalyesi.png"
  },
  {
    "id": 34,
    "name": "Kılıç Kraliçesi",
    "front": "Kılıç Kraliçesi",
    "revert": "Kılıç Kraliçesi Ters",
    "enFront": "Queen of Swords",
    "enRevert": "Queen of Swords - revert",
    "image": "falfalFE/public/images/cards/kilic-kralicesi.png"
  },
  {
    "id": 35,
    "name": "Kılıç Kralı",
    "front": "Kılıç Kralı",
    "revert": "Kılıç Kralı Ters",
    "enFront": "King of Swords",
    "enRevert": "King of Swords - revert",
    "image": "falfalFE/public/images/cards/kilic-krali.png"
  },
  {
    "id": 36,
    "name": "Asa Ası",
    "front": "Asa Ası",
    "revert": "Asa Ası Ters",
    "enFront": "Ace of Wands",
    "enRevert": "Ace of Wands - revert",
    "image": "falfalFE/public/images/cards/asa-asi.png"
  },
  {
    "id": 37,
    "name": "Asa İkilisi",
    "front": "Asa İkilisi",
    "revert": "Asa İkilisi Ters",
    "enFront": "Two of Wands",
    "enRevert": "Two of Wands - revert",
    "image": "falfalFE/public/images/cards/asa-ikilisi.png"
  },
  {
    "id": 38,
    "name": "Asa Üçlüsü",
    "front": "Asa Üçlüsü",
    "revert": "Asa Üçlüsü Ters",
    "enFront": "Three of Wands",
    "enRevert": "Three of Wands - revert",
    "image": "falfalFE/public/images/cards/asa-uclusu.png"
  },
  {
    "id": 39,
    "name": "Asa Dörtlüsü",
    "front": "Asa Dörtlüsü",
    "revert": "Asa Dörtlüsü Ters",
    "enFront": "Four of Wands",
    "enRevert": "Four of Wands - revert",
    "image": "falfalFE/public/images/cards/asa-dortlusu.png"
  },
  {
    "id": 40,
    "name": "Asa Beşlisi",
    "front": "Asa Beşlisi",
    "revert": "Asa Beşlisi Ters",
    "enFront": "Five of Wands",
    "enRevert": "Five of Wands - revert",
    "image": "falfalFE/public/images/cards/asa-beslisi.png"
  },
  {
    "id": 41,
    "name": "Asa Altılısı",
    "front": "Asa Altılısı",
    "revert": "Asa Altılısı Ters",
    "enFront": "Six of Wands",
    "enRevert": "Six of Wands - revert",
    "image": "falfalFE/public/images/cards/asa-altilisi.png"
  },
  {
    "id": 42,
    "name": "Asa Yedilisi",
    "front": "Asa Yedilisi",
    "revert": "Asa Yedilisi Ters
    "enFront": "Seven of Wands",
    "enRevert": "Seven of Wands - revert",
    "image": "falfalFE/public/images/cards/asa-yedilisi.png"
  },
  {
    "id": 43,
    "name": "Asa Sekizlisi",
    "front": "Asa Sekizlisi",
    "revert": "Asa Sekizlisi Ters",
    "enFront": "Eight of Wands",
    "enRevert": "Eight of Wands - revert",
    "image": "falfalFE/public/images/cards/asa-sekizlisi.png"
  },
  {
    "id": 44,
    "name": "Asa Dokuzlusu",
    "front": "Asa Dokuzlusu",
    "revert": "Asa Dokuzlusu Ters",
    "enFront": "Nine of Wands",
    "enRevert": "Nine of Wands - revert",
    "image": "falfalFE/public/images/cards/asa-dokuzlusu.png"
  },
  {
    "id": 45,
    "name": "Asa Onlusu",
    "front": "Asa Onlusu",
    "revert": "Asa Onlusu Ters",
    "enFront": "Ten of Wands",
    "enRevert": "Ten of Wands - revert",
    "image": "falfalFE/public/images/cards/asa-onlusu.png"
  },
  {
    "id": 46,
    "name": "Asa Prensi",
    "front": "Asa Prensi",
    "revert": "Asa Prensi Ters",
    "enFront": "Page of Wands",
    "enRevert": "Page of Wands - revert",
    "image": "falfalFE/public/images/cards/asa-prensi.png"
  },
  {
    "id": 47,
    "name": "Asa Şövalyesi",
    "front": "Asa Şövalyesi",
    "revert": "Asa Şövalyesi Ters",
    "enFront": "Knight of Wands",
    "enRevert": "Knight of Wands - revert",
    "image": "falfalFE/public/images/cards/asa-sovalyesi.png"
  },
  {
    "id": 48,
    "name": "Asa Kraliçesi",
    "front": "Asa Kraliçesi",
    "revert": "Asa Kraliçesi Ters",
    "enFront": "Queen of Wands",
    "enRevert": "Queen of Wands - revert",
    "image": "falfalFE/public/images/cards/asa-kralicesi.png"
  },
  {
    "id": 49,
    "name": "Asa Kralı",
    "front": "Asa Kralı",
    "revert": "Asa Kralı Ters",
    "enFront": "King of Wands",
    "enRevert": "King of Wands - revert",
    "image": "falfalFE/public/images/cards/asa-krali.png"
  }
]